{
  "updated": "2026-04-17 00:54 UTC",
  "prices": {
    "IE000QAZP7L2": 12.497,
    "IE000ZYRH0Q7": 11.016,
    "LU0034353002": 93.39,
    "IE00BFZMJT78": 118.28,
    "LU1694789451": 130.51,
    "ES0140794001": 13.70411,
    "ES0175902008": 20.10268,
    "ES0112231016": 29.50962
  },
  "history": [
    {
      "date": "2025-01-01",
      "total": 22603.41
    },
    {
      "date": "2025-12-31",
      "total": 23259.3
    },
    {
      "date": "2026-01-31",
      "total": 24037.81
    },
    {
      "date": "2026-02-28",
      "total": 24219.57
    },
    {
      "date": "2026-03-31",
      "total": 24403.1
    },
    {
      "date": "2026-04-16",
      "total": 23901.64
    },
    {
      "date": "2026-04-17",
      "total": 24003.34
    }
  ]
}